django_media_fixtures/__init__.py
django_media_fixtures/finders.py
django_media_fixtures/management/__init__.py
django_media_fixtures/management/commands/__init__.py
django_media_fixtures/management/commands/collectmedia.py
django_media_fixtures/tests/__init__.py
django_media_fixtures/tests/settings.py
django_media_fixtures/tests/testapp/__init__.py
django_media_fixtures/tests/testapp/apps.py
django_media_fixtures/tests/testapp/models.py
django_media_fixtures/tests/testapp/tests.py
sweelol-1.2.1.dist-info/LICENSE
sweelol-1.2.1.dist-info/METADATA
sweelol-1.2.1.dist-info/WHEEL
sweelol-1.2.1.dist-info/entry_points.txt
sweelol-1.2.1.dist-info/top_level.txt
sweelol-1.2.1.dist-info/RECORD
